{
  "$schema": "https://developer.microsoft.com/json-schemas/fabric/item/report/definition/visualContainer/2.8.0/schema.json",
  "name": "aa694f5bc3410045eb59",
  "position": {
    "x": 1061.1940298507463,
    "y": 58.208955223880594,
    "z": 2000,
    "height": 44.776119402985074,
    "width": 209.55223880597015,
    "tabOrder": 2000
  },
  "visual": {
    "visualType": "slicer",
    "query": {
      "queryState": {
        "Values": {
          "projections": [
            {
              "field": {
                "Column": {
                  "Expression": {
                    "SourceRef": {
                      "Entity": "Calendario"
                    }
                  },
                  "Property": "Date"
                }
              },
              "queryRef": "Calendario.Date",
              "nativeQueryRef": "Date",
              "active": true
            }
          ]
        }
      },
      "sortDefinition": {
        "sort": [
          {
            "field": {
              "Column": {
                "Expression": {
                  "SourceRef": {
                    "Entity": "Calendario"
                  }
                },
                "Property": "Date"
              }
            },
            "direction": "Ascending"
          }
        ],
        "isDefaultSort": true
      }
    },
    "objects": {
      "data": [
        {
          "properties": {
            "startDate": {
              "expr": {
                "Literal": {
                  "Value": "datetime'2026-05-05T00:00:00'"
                }
              }
            },
            "mode": {
              "expr": {
                "Literal": {
                  "Value": "'Between'"
                }
              }
            }
          }
        }
      ],
      "general": [
        {
          "properties": {
            "filter": {
              "filter": {
                "Version": 2,
                "From": [
                  {
                    "Name": "c",
                    "Entity": "Calendario",
                    "Type": 0
                  }
                ],
                "Where": [
                  {
                    "Condition": {
                      "Comparison": {
                        "ComparisonKind": 2,
                        "Left": {
                          "Column": {
                            "Expression": {
                              "SourceRef": {
                                "Source": "c"
                              }
                            },
                            "Property": "Date"
                          }
                        },
                        "Right": {
                          "Literal": {
                            "Value": "datetime'2026-05-05T00:00:00'"
                          }
                        }
                      }
                    }
                  }
                ]
              }
            }
          }
        }
      ],
      "header": [
        {
          "properties": {
            "show": {
              "expr": {
                "Literal": {
                  "Value": "false"
                }
              }
            }
          }
        }
      ]
    },
    "drillFilterOtherVisuals": true
  }
}